{
  "generatedAt": "2026-04-14T03:41:00Z",
  "source": {
    "sessionsList": {
      "limit": 50,
      "messageLimit": 1,
      "count": 12
    },
    "subagents": {
      "recentMinutes": 1440,
      "active": 0,
      "recent": 0
    }
  },
  "priorities": [
    "Keep main agent stable and responsive",
    "Re-activate specialist agents only on demand",
    "Investigate failed specialist sessions before next dispatch"
  ],
  "goalProgress": {
    "main": "Operational with active cron runtime",
    "contactenrichment": "Last enrichment run completed and awaiting next queue",
    "linkedin": "Idle with one failed slash session requiring follow-up",
    "n8n": "Standby with no active automation run",
    "flowise": "Standby waiting for new flow requests"
  },
  "agents": [
    {
      "name": "main",
      "label": "Aisha",
      "status": "Active",
      "health": "ok",
      "goal": "Coordinate mission control and user-facing orchestration",
      "task": "Cron refresh session currently running",
      "pending": "Review older failed slash sessions for model compatibility"
    },
    {
      "name": "contactenrichment",
      "label": "contactenrichment",
      "status": "Idle/Standby",
      "health": "warn",
      "goal": "Fill missing school contact fields from official sources",
      "task": "Recent batch completed with final metrics returned",
      "pending": "Await next Notion-backed enrichment queue"
    },
    {
      "name": "linkedin",
      "label": "linkedin",
      "status": "Idle/Standby",
      "health": "bad",
      "goal": "Run LinkedIn lookup and profile enrichment on demand",
      "task": "No running session; latest group task ended",
      "pending": "Investigate failed slash session before next run"
    },
    {
      "name": "n8n",
      "label": "n8n",
      "status": "Idle/Standby",
      "health": "warn",
      "goal": "Execute and deploy automation workflows",
      "task": "No running session detected",
      "pending": "Waiting for new automation tasks"
    },
    {
      "name": "flowise",
      "label": "flowise",
      "status": "Idle/Standby",
      "health": "warn",
      "goal": "Handle Flowise build and support requests",
      "task": "No running session detected",
      "pending": "Waiting for new flow requests"
    }
  ]
}
