{
  "generatedAt": "2026-04-14T01:31:00Z",
  "source": {
    "sessions": "sessions_list(limit=50,messageLimit=1)",
    "subagents": "subagents(action=list,recentMinutes=1440)"
  },
  "priorities": [
    "Keep main (Aisha) stable while cron refresh runs",
    "Re-activate specialist agents only on incoming work",
    "Monitor linkedin reliability after prior failed runs"
  ],
  "goalProgress": [
    {
      "goal": "Mission control runtime visibility",
      "status": "on_track",
      "note": "Live dashboard refreshed from current OpenClaw session state"
    },
    {
      "goal": "Specialist agent utilization",
      "status": "needs_attention",
      "note": "No specialist agent is currently running"
    }
  ],
  "agents": [
    {
      "name": "main",
      "displayName": "Aisha",
      "status": "Active",
      "health": "ok",
      "goal": "Coordinate ops and keep mission control current",
      "task": "Cron live-data refresh session is running",
      "pending": "Finish refresh cycle and keep orchestration stable"
    },
    {
      "name": "contactenrichment",
      "displayName": "contactenrichment",
      "status": "Idle/Standby",
      "health": "warn",
      "goal": "Enrich school contact data from verified sources",
      "task": "Last run completed with final enrichment summary",
      "pending": "Await next Notion enrichment batch"
    },
    {
      "name": "linkedin",
      "displayName": "linkedin",
      "status": "Idle/Standby",
      "health": "bad",
      "goal": "Run LinkedIn discovery and profile mapping",
      "task": "No active run; failed session present in recent history",
      "pending": "Retry on next lookup request and confirm stability"
    },
    {
      "name": "n8n",
      "displayName": "n8n",
      "status": "Idle/Standby",
      "health": "warn",
      "goal": "Build and deploy automation workflows",
      "task": "No active session",
      "pending": "Await next automation assignment"
    },
    {
      "name": "flowise",
      "displayName": "flowise",
      "status": "Idle/Standby",
      "health": "warn",
      "goal": "Support Flowise pipeline operations",
      "task": "No active session",
      "pending": "Await next Flowise task"
    }
  ]
}
