{
  "generatedAt": "2026-04-14T02:55:00Z",
  "source": {
    "sessions": "sessions_list(limit=50,messageLimit=1)",
    "subagents": "subagents(action=list,recentMinutes=1440)",
    "sessionCount": 12,
    "subagentActive": 0
  },
  "priorities": [
    "Keep main (Aisha) responsive for active cron and operator requests",
    "Unblock contactenrichment Notion integration before next enrichment run",
    "Keep linkedin, n8n, and flowise ready for task dispatch"
  ],
  "goalProgress": [
    {
      "agent": "main",
      "goal": "Mission-control live refresh and orchestration",
      "status": "in_progress",
      "progress": "Running current cron refresh"
    },
    {
      "agent": "contactenrichment",
      "goal": "School contact enrichment in Notion",
      "status": "pending",
      "progress": "Awaiting Notion integration access; last completed run processed 99 rows"
    },
    {
      "agent": "linkedin",
      "goal": "LinkedIn lookup/update support",
      "status": "standby",
      "progress": "No active run; awaiting new lookup batch"
    },
    {
      "agent": "n8n",
      "goal": "Automation workflow execution",
      "status": "standby",
      "progress": "No active run; awaiting automation task"
    },
    {
      "agent": "flowise",
      "goal": "Flowise build/support",
      "status": "standby",
      "progress": "No active run; awaiting new build request"
    }
  ],
  "agents": [
    {
      "name": "main",
      "display": "Aisha",
      "status": "Active",
      "health": "ok",
      "task": "Running mission-control-live-data-refresh cron",
      "pending": "Continue orchestration and dashboard refresh"
    },
    {
      "name": "contactenrichment",
      "display": "Contact Enrichment",
      "status": "Standby",
      "health": "warn",
      "task": "Notion school contact enrichment",
      "pending": "Confirm Notion API key and integration share before next run"
    },
    {
      "name": "linkedin",
      "display": "LinkedIn",
      "status": "Standby",
      "health": "warn",
      "task": "LinkedIn lookup/update support",
      "pending": "Awaiting new assignment"
    },
    {
      "name": "n8n",
      "display": "n8n",
      "status": "Standby",
      "health": "warn",
      "task": "Automation workflow execution",
      "pending": "Awaiting deployment or execution task"
    },
    {
      "name": "flowise",
      "display": "Flowise",
      "status": "Standby",
      "health": "warn",
      "task": "Flowise build/support",
      "pending": "Awaiting new build request"
    }
  ]
}
